{
  "dataset": "cleveland",
  "model": "lr",
  "mode": "tuning",
  "fold": null,
  "seed": 42,
  "epochs": 100,
  "learning_rate": 0.0001,
  "rank": null,
  "interaction_order": null,
  "batch_size": 512,
  "num_workers": 4,
  "accelerator": "gpu",
  "early_stopping": true,
  "patience": 15,
  "monitor": "val_loss",
  "monitor_mode": "min",
  "best_model_path": "/zhome/58/0/217144/Fagprojekt/src/summary_results/results/lr/tuning_cleveland_lr_combo0/checkpoints/best.ckpt",
  "best_model_score": 1.5082783699035645,
  "stopped_epoch": 100,
  "skip_test": true,
  "num_classes": 5,
  "input_dim": 34,
  "trainable_parameters": 175,
  "fit_seconds": 56.566214373800904,
  "test_seconds": null
}
